squall/__init__.py
squall/database_structure_tree.py
squall/db_utility.py
squall/edit_row.py
squall/execute_sql.py
squall/screens.py
squall/squall.py
squall/squall.tcss
squall/table_viewer.py
squall_sql-0.1.8.dist-info/METADATA
squall_sql-0.1.8.dist-info/WHEEL
squall_sql-0.1.8.dist-info/entry_points.txt
squall_sql-0.1.8.dist-info/licenses/LICENSE
squall_sql-0.1.8.dist-info/RECORD
