Metadata-Version: 2.4
Name: squall_sql
Version: 0.1.8
Summary: Squall - SQLite Editor
Project-URL: Homepage, https://github.com/driscollis/squall
Project-URL: Documentation, https://github.com/driscollis/squall/blob/main/README.md
Project-URL: Repository, https://github.com/driscollis/squall
Project-URL: Issues, https://github.com/driscollis/squall/issues
Project-URL: Discussions, https://github.com/driscollis/squall/discussions
Project-URL: Wiki, https://github.com/driscollis/squall/wiki
Author-email: Mike Driscoll <mike@pythonlibrary.org>
Maintainer-email: Mike Driscoll <mike@pythonlibrary.org>
License: MIT License
License-File: LICENSE
Keywords: sql,sqlite,terminal,tui
Classifier: Development Status :: 4 - Beta
Classifier: Environment :: Console
Classifier: Intended Audience :: Developers
Classifier: Intended Audience :: End Users/Desktop
Classifier: Intended Audience :: Other Audience
Classifier: License :: OSI Approved :: MIT License
Classifier: Operating System :: MacOS
Classifier: Operating System :: Microsoft :: Windows :: Windows 10
Classifier: Operating System :: Microsoft :: Windows :: Windows 11
Classifier: Operating System :: POSIX :: Linux
Classifier: Programming Language :: Python :: 3
Classifier: Programming Language :: Python :: 3.11
Classifier: Programming Language :: Python :: 3.12
Classifier: Programming Language :: Python :: 3.13
Classifier: Topic :: Software Development :: Libraries :: Python Modules
Classifier: Typing :: Typed
Requires-Python: >=3.11
Requires-Dist: rich>=13.9.4
Requires-Dist: sqlalchemy>=2.0.38
Requires-Dist: textual>=2.1.1
